{
  "data": {
    "archetypes": [
      {
        "id": 155,
        "name": "Mythical Beast",
        "slug": "mythical-beast",
        "type": "archetype",
        "image": "https://cardcluster.com/storage/cards/MP19/MP19-DE121-ea1de27c31",
        "isFirstPrint": true
      },
      {
        "id": 858,
        "name": "Yugi Muto | Yami Yugi",
        "slug": "yugi-muto-yami-yugi",
        "type": "character",
        "image": "https://cardcluster.com/storage/cards/MP22/MP22-EN273-69e63915d2",
        "isFirstPrint": false
      },
      {
        "id": 702,
        "name": "Marik Ishtar | Yami Marik",
        "slug": "marik-ishtar-yami-marik",
        "type": "character",
        "image": "https://cardcluster.com/storage/cards/LED7/LED7-DE005-d1440640ac",
        "isFirstPrint": false
      },
      {
        "id": 799,
        "name": "Yusei Fudo",
        "slug": "yusei-fudo",
        "type": "character",
        "image": "https://cardcluster.com/storage/cards/OP16/OP16-DE025-784a52b541",
        "isFirstPrint": false
      },
      {
        "id": 926,
        "name": "Bonz",
        "slug": "bonz",
        "type": "character",
        "image": "https://cardcluster.com/storage/cards/MRD/MRD-G079-dfe01ad810",
        "isFirstPrint": false
      }
    ],
    "archetypesReprint": [
      {
        "id": 45,
        "name": "Dark Magician",
        "slug": "dark-magician",
        "type": "archetype",
        "image": "https://cardcluster.com/storage/cards/RA04/RA04-EN054-SCR-a69055b778",
        "isFirstPrint": false
      },
      {
        "id": 871,
        "name": "Alexis Rhodes",
        "slug": "alexis-rhodes",
        "type": "character",
        "image": "https://cardcluster.com/storage/cards/LDS2/LDS2-EN093-a66d7170b0",
        "isFirstPrint": false
      },
      {
        "id": 827,
        "name": "Chazz Princeton",
        "slug": "chazz-princeton",
        "type": "character",
        "image": "https://cardcluster.com/storage/cards/BLMR/BLMR-EN002-SCR-8498b5d6a6",
        "isFirstPrint": false
      },
      {
        "id": 541,
        "name": "Spirit",
        "slug": "spirit",
        "type": "series",
        "image": "https://cardcluster.com/storage/cards/BLMR/BLMR-EN070-94a16c67df",
        "isFirstPrint": false
      },
      {
        "id": 695,
        "name": "Chaos",
        "slug": "chaos",
        "type": "series",
        "image": "https://cardcluster.com/storage/cards/RA01/RA01-EN065-SCR-ae1baf3a05",
        "isFirstPrint": false
      },
      {
        "id": 801,
        "name": "Yubel (character)",
        "slug": "yubel-character",
        "type": "character",
        "image": "https://cardcluster.com/storage/cards/LEDE/LEDE-EN061-UR-e05dd42848",
        "isFirstPrint": false
      },
      {
        "id": 781,
        "name": "Bastion Misawa",
        "slug": "bastion-misawa",
        "type": "character",
        "image": "https://cardcluster.com/storage/cards/BLRR/BLRR-DE013-60e8955331",
        "isFirstPrint": false
      },
      {
        "id": 770,
        "name": "Reggie MacKenzie",
        "slug": "reggie-mackenzie",
        "type": "character",
        "image": "https://cardcluster.com/storage/cards/SDLS/SDLS-DE009-f106678fff",
        "isFirstPrint": false
      },
      {
        "id": 778,
        "name": "Midori Hibiki",
        "slug": "midori-hibiki",
        "type": "character",
        "image": "https://cardcluster.com/storage/cards/YG05/YG05-EN001-30b15fc3f8",
        "isFirstPrint": false
      },
      {
        "id": 813,
        "name": "Reginald \"Shark\" Kastle | Nash",
        "slug": "reginald-shark-kastle-nash",
        "type": "character",
        "image": "https://cardcluster.com/storage/cards/LED9/LED9-EN005-f4211008d2",
        "isFirstPrint": false
      },
      {
        "id": 812,
        "name": "Yugo",
        "slug": "yugo",
        "type": "character",
        "image": "https://cardcluster.com/storage/cards/SUDA/SUDA-DE068-23cd0f1cc7",
        "isFirstPrint": false
      },
      {
        "id": 876,
        "name": "Seto Kaiba",
        "slug": "seto-kaiba",
        "type": "character",
        "image": "https://cardcluster.com/storage/cards/LDS2/LDS2-EN029-UR-6737cf8624",
        "isFirstPrint": false
      },
      {
        "id": 883,
        "name": "Jaden Yuki",
        "slug": "jaden-yuki",
        "type": "character",
        "image": "https://cardcluster.com/storage/cards/MP23/MP23-DE137-f9450a67ca",
        "isFirstPrint": false
      },
      {
        "id": 911,
        "name": "Syrus Truesdale",
        "slug": "syrus-truesdale",
        "type": "character",
        "image": "https://cardcluster.com/storage/cards/SGX2/SGX2-ENB24-5cc198ef63",
        "isFirstPrint": false
      },
      {
        "id": 784,
        "name": "Greiger",
        "slug": "greiger",
        "type": "character",
        "image": "https://cardcluster.com/storage/cards/CRMS/CRMS-EN016-4fcd72ab5d",
        "isFirstPrint": false
      },
      {
        "id": 841,
        "name": "Gansley",
        "slug": "gansley",
        "type": "character",
        "image": "https://cardcluster.com/storage/cards/PSV/PSV-G079-77f06b12e2",
        "isFirstPrint": false
      },
      {
        "id": 701,
        "name": "Yami Bakura",
        "slug": "yami-bakura",
        "type": "character",
        "image": "https://cardcluster.com/storage/cards/LDS3/LDS3-DE021-7aefc0eb4a",
        "isFirstPrint": false
      },
      {
        "id": 802,
        "name": "Kagemaru",
        "slug": "kagemaru",
        "type": "character",
        "image": "https://cardcluster.com/storage/cards/SGX3/SGX3-DEG15-a2acf4a0e0",
        "isFirstPrint": false
      },
      {
        "id": 838,
        "name": "Joey Wheeler",
        "slug": "joey-wheeler",
        "type": "character",
        "image": "https://cardcluster.com/storage/cards/ROTA/ROTA-EN072-6904749327",
        "isFirstPrint": false
      },
      {
        "id": 697,
        "name": "Ishizu Ishtar",
        "slug": "ishizu-ishtar",
        "type": "character",
        "image": "https://cardcluster.com/storage/cards/MAMA/MAMA-EN029-4c17477a57",
        "isFirstPrint": false
      },
      {
        "id": 785,
        "name": "Luna",
        "slug": "luna",
        "type": "character",
        "image": "https://cardcluster.com/storage/cards/ALIN/ALIN-DE071-eebc3d5a2d",
        "isFirstPrint": false
      },
      {
        "id": 866,
        "name": "Odion",
        "slug": "odion",
        "type": "character",
        "image": "https://cardcluster.com/storage/cards/MZTM/MZTM-DE001-SCR-c901c641a0",
        "isFirstPrint": false
      },
      {
        "id": 919,
        "name": "Yuma Tsukumo | Astral",
        "slug": "yuma-tsukumo-astral",
        "type": "character",
        "image": "https://cardcluster.com/storage/cards/DUPO/DUPO-DE010-5374889f7b",
        "isFirstPrint": false
      },
      {
        "id": 774,
        "name": "Roman Goodwin",
        "slug": "roman-goodwin",
        "type": "character",
        "image": "https://cardcluster.com/storage/cards/LDS3/LDS3-DE043-b68de190bd",
        "isFirstPrint": false
      },
      {
        "id": 815,
        "name": "Alito",
        "slug": "alito",
        "type": "character",
        "image": "https://cardcluster.com/storage/cards/LD10/LD10-EN037-3c76f03baa",
        "isFirstPrint": false
      },
      {
        "id": 782,
        "name": "Jim Crocodile Cook",
        "slug": "jim-crocodile-cook",
        "type": "character",
        "image": "",
        "isFirstPrint": false
      },
      {
        "id": 773,
        "name": "Sect Ijuin",
        "slug": "sect-ijuin",
        "type": "character",
        "image": "https://cardcluster.com/storage/cards/YF08/YF08-EN001-7f0ef3dc54",
        "isFirstPrint": false
      },
      {
        "id": 821,
        "name": "Rex Goodwin",
        "slug": "rex-goodwin",
        "type": "character",
        "image": "https://cardcluster.com/storage/cards/LDS3/LDS3-DE061-f81c9d2cb3",
        "isFirstPrint": false
      },
      {
        "id": 872,
        "name": "Roken Kogami | Varis",
        "slug": "roken-kogami-varis",
        "type": "character",
        "image": "https://cardcluster.com/storage/tmp/TMP-CARD-14153-60af400fa6-a06fe24706",
        "isFirstPrint": false
      }
    ],
    "category": {
      "name": "Structure Decks",
      "slug": "structure-decks",
      "sets": [
        {
          "image": null,
          "format": 1,
          "name": "THE CHRONICLES DECK: Spirit Charmers (All-Foil Edition)",
          "releaseEu": "2026-01-22T00:00:00.000000Z",
          "releaseEuDayUnknown": false,
          "releaseEuMonthUnknown": false,
          "releaseNa": "2026-01-23T00:00:00.000000Z",
          "releaseNaDayUnknown": false,
          "releaseNaMonthUnknown": false,
          "tcgNotConfirmed": false,
          "setNumber": "CH02",
          "slug": "the-chronicles-deck-spirit-charmers-all-foil-edition",
          "cardSlugs": null,
          "artworkIds": null,
          "printsCount": null,
          "spoilerTotalPrints": 50
        },
        {
          "image": null,
          "format": 1,
          "name": "THE CHRONICLES DECK: The Fallen & The Virtuous (All-Foil Edition)",
          "releaseEu": "2025-10-23T00:00:00.000000Z",
          "releaseEuDayUnknown": false,
          "releaseEuMonthUnknown": false,
          "releaseNa": "2025-10-24T00:00:00.000000Z",
          "releaseNaDayUnknown": false,
          "releaseNaMonthUnknown": false,
          "tcgNotConfirmed": false,
          "setNumber": "CH01",
          "slug": "the-chronicles-deck-the-fallen-the-virtuous-all-foil-edition",
          "cardSlugs": null,
          "artworkIds": null,
          "printsCount": null,
          "spoilerTotalPrints": 50
        },
        {
          "image": "https://cardcluster.com/storage/sets/SDWD-c221e4a586eccbd15722",
          "format": 1,
          "name": "Structure Deck: Blue-Eyes White Destiny",
          "releaseEu": "2025-02-13T00:00:00.000000Z",
          "releaseEuDayUnknown": false,
          "releaseEuMonthUnknown": false,
          "releaseNa": "2025-02-14T00:00:00.000000Z",
          "releaseNaDayUnknown": false,
          "releaseNaMonthUnknown": false,
          "tcgNotConfirmed": false,
          "setNumber": "SDWD",
          "slug": "structure-deck-blue-eyes-white-destiny",
          "cardSlugs": null,
          "artworkIds": null,
          "printsCount": null,
          "spoilerTotalPrints": null
        },
        {
          "image": "https://cardcluster.com/storage/sets/SDCK-57a3c134017ed6b2f2b8",
          "format": 1,
          "name": "Structure Deck: The Crimson King",
          "releaseEu": "2023-09-21T00:00:00.000000Z",
          "releaseEuDayUnknown": false,
          "releaseEuMonthUnknown": false,
          "releaseNa": "2023-09-22T00:00:00.000000Z",
          "releaseNaDayUnknown": false,
          "releaseNaMonthUnknown": false,
          "tcgNotConfirmed": false,
          "setNumber": "SDCK",
          "slug": "structure-deck-the-crimson-king",
          "cardSlugs": null,
          "artworkIds": null,
          "printsCount": null,
          "spoilerTotalPrints": null
        },
        {
          "image": "https://cardcluster.com/storage/sets/SDBT-0bf1f001f63e2cb96249",
          "format": 1,
          "name": "Structure Deck: Beware of Traptrix",
          "releaseEu": "2023-02-23T00:00:00.000000Z",
          "releaseEuDayUnknown": false,
          "releaseEuMonthUnknown": false,
          "releaseNa": "2023-02-24T00:00:00.000000Z",
          "releaseNaDayUnknown": false,
          "releaseNaMonthUnknown": false,
          "tcgNotConfirmed": false,
          "setNumber": "SDBT",
          "slug": "structure-deck-beware-of-traptrix",
          "cardSlugs": null,
          "artworkIds": null,
          "printsCount": null,
          "spoilerTotalPrints": null
        },
        {
          "image": "https://cardcluster.com/storage/sets/SDCB-292f8787edf5644441f0",
          "format": 1,
          "name": "Structure Deck: Legend of the Crystal Beasts",
          "releaseEu": "2022-09-29T00:00:00.000000Z",
          "releaseEuDayUnknown": false,
          "releaseEuMonthUnknown": false,
          "releaseNa": "2022-09-30T00:00:00.000000Z",
          "releaseNaDayUnknown": false,
          "releaseNaMonthUnknown": false,
          "tcgNotConfirmed": false,
          "setNumber": "SDCB",
          "slug": "structure-deck-legend-of-the-crystal-beasts",
          "cardSlugs": null,
          "artworkIds": null,
          "printsCount": null,
          "spoilerTotalPrints": null
        },
        {
          "image": "https://cardcluster.com/storage/sets/SDAZ-53877363b7776af1d1c6",
          "format": 1,
          "name": "Structure Deck: Albaz Strike",
          "releaseEu": "2022-04-14T00:00:00.000000Z",
          "releaseEuDayUnknown": false,
          "releaseEuMonthUnknown": false,
          "releaseNa": "2022-04-15T00:00:00.000000Z",
          "releaseNaDayUnknown": false,
          "releaseNaMonthUnknown": false,
          "tcgNotConfirmed": false,
          "setNumber": "SDAZ",
          "slug": "structure-deck-albaz-strike",
          "cardSlugs": null,
          "artworkIds": null,
          "printsCount": null,
          "spoilerTotalPrints": null
        },
        {
          "image": "https://cardcluster.com/storage/sets/SDCS-14d2b50b32421763c8b3",
          "format": 1,
          "name": "Structure Deck: Cyber Strike",
          "releaseEu": "2021-10-14T00:00:00.000000Z",
          "releaseEuDayUnknown": false,
          "releaseEuMonthUnknown": false,
          "releaseNa": "2021-10-15T00:00:00.000000Z",
          "releaseNaDayUnknown": false,
          "releaseNaMonthUnknown": false,
          "tcgNotConfirmed": false,
          "setNumber": "SDCS",
          "slug": "structure-deck-cyber-strike",
          "cardSlugs": null,
          "artworkIds": null,
          "printsCount": null,
          "spoilerTotalPrints": null
        },
        {
          "image": "https://cardcluster.com/storage/sets/SDFC-2224d04df26898180790",
          "format": 1,
          "name": "Structure Deck: Freezing Chains",
          "releaseEu": "2021-02-18T00:00:00.000000Z",
          "releaseEuDayUnknown": false,
          "releaseEuMonthUnknown": false,
          "releaseNa": "2021-02-19T00:00:00.000000Z",
          "releaseNaDayUnknown": false,
          "releaseNaMonthUnknown": false,
          "tcgNotConfirmed": false,
          "setNumber": "SDFC",
          "slug": "structure-deck-freezing-chains",
          "cardSlugs": null,
          "artworkIds": null,
          "printsCount": null,
          "spoilerTotalPrints": null
        },
        {
          "image": "https://cardcluster.com/storage/sets/SDCH-b1525a85b35a3c172731",
          "format": 1,
          "name": "Structure Deck: Spirit Charmers",
          "releaseEu": "2020-10-22T00:00:00.000000Z",
          "releaseEuDayUnknown": false,
          "releaseEuMonthUnknown": false,
          "releaseNa": "2020-11-20T00:00:00.000000Z",
          "releaseNaDayUnknown": false,
          "releaseNaMonthUnknown": false,
          "tcgNotConfirmed": false,
          "setNumber": "SDCH",
          "slug": "structure-deck-spirit-charmers",
          "cardSlugs": null,
          "artworkIds": null,
          "printsCount": null,
          "spoilerTotalPrints": null
        },
        {
          "image": "https://cardcluster.com/storage/sets/SDSA-67b3c719cd13d13ac1bf",
          "format": 1,
          "name": "Structure Deck: Sacred Beasts",
          "releaseEu": "2020-07-09T00:00:00.000000Z",
          "releaseEuDayUnknown": false,
          "releaseEuMonthUnknown": false,
          "releaseNa": "2020-07-10T00:00:00.000000Z",
          "releaseNaDayUnknown": false,
          "releaseNaMonthUnknown": false,
          "tcgNotConfirmed": false,
          "setNumber": "SDSA",
          "slug": "structure-deck-sacred-beasts",
          "cardSlugs": null,
          "artworkIds": null,
          "printsCount": null,
          "spoilerTotalPrints": null
        },
        {
          "image": "https://cardcluster.com/storage/sets/SDSH-30da7b309d60823456ef",
          "format": 1,
          "name": "Structure Deck: Shaddoll Showdown",
          "releaseEu": "2020-02-13T00:00:00.000000Z",
          "releaseEuDayUnknown": false,
          "releaseEuMonthUnknown": false,
          "releaseNa": "2020-02-14T00:00:00.000000Z",
          "releaseNaDayUnknown": false,
          "releaseNaMonthUnknown": false,
          "tcgNotConfirmed": false,
          "setNumber": "SDSH",
          "slug": "structure-deck-shaddoll-showdown",
          "cardSlugs": null,
          "artworkIds": null,
          "printsCount": null,
          "spoilerTotalPrints": null
        },
        {
          "image": "https://cardcluster.com/storage/sets/SDRR-f0408a7167e0b8e8b059",
          "format": 1,
          "name": "Structure Deck: Rokket Revolt",
          "releaseEu": "2019-08-15T00:00:00.000000Z",
          "releaseEuDayUnknown": false,
          "releaseEuMonthUnknown": false,
          "releaseNa": "2019-08-16T00:00:00.000000Z",
          "releaseNaDayUnknown": false,
          "releaseNaMonthUnknown": false,
          "tcgNotConfirmed": false,
          "setNumber": "SDRR",
          "slug": "structure-deck-rokket-revolt",
          "cardSlugs": null,
          "artworkIds": null,
          "printsCount": null,
          "spoilerTotalPrints": null
        },
        {
          "image": "https://cardcluster.com/storage/sets/SDSB-7365a8e4036b4fa01a37",
          "format": 1,
          "name": "Structure Deck: Soulburner",
          "releaseEu": "2019-02-14T00:00:00.000000Z",
          "releaseEuDayUnknown": false,
          "releaseEuMonthUnknown": false,
          "releaseNa": "2019-02-15T00:00:00.000000Z",
          "releaseNaDayUnknown": false,
          "releaseNaMonthUnknown": false,
          "tcgNotConfirmed": false,
          "setNumber": "SDSB",
          "slug": "structure-deck-soulburner",
          "cardSlugs": null,
          "artworkIds": null,
          "printsCount": null,
          "spoilerTotalPrints": null
        },
        {
          "image": null,
          "format": 1,
          "name": "Structure Deck: Powercode Link",
          "releaseEu": "2018-08-09T00:00:00.000000Z",
          "releaseEuDayUnknown": false,
          "releaseEuMonthUnknown": false,
          "releaseNa": "2018-08-10T00:00:00.000000Z",
          "releaseNaDayUnknown": false,
          "releaseNaMonthUnknown": false,
          "tcgNotConfirmed": false,
          "setNumber": "SDPL",
          "slug": "structure-deck-powercode-link",
          "cardSlugs": null,
          "artworkIds": null,
          "printsCount": null,
          "spoilerTotalPrints": null
        },
        {
          "image": null,
          "format": 1,
          "name": "Structure Deck: Cyberse Link",
          "releaseEu": "2017-11-02T00:00:00.000000Z",
          "releaseEuDayUnknown": false,
          "releaseEuMonthUnknown": false,
          "releaseNa": "2017-11-03T00:00:00.000000Z",
          "releaseNaDayUnknown": false,
          "releaseNaMonthUnknown": false,
          "tcgNotConfirmed": false,
          "setNumber": "SDCL",
          "slug": "structure-deck-cyberse-link",
          "cardSlugs": null,
          "artworkIds": null,
          "printsCount": null,
          "spoilerTotalPrints": null
        },
        {
          "image": null,
          "format": 1,
          "name": "Pendulum Domination Structure Deck",
          "releaseEu": "2017-01-19T00:00:00.000000Z",
          "releaseEuDayUnknown": false,
          "releaseEuMonthUnknown": false,
          "releaseNa": "2017-01-20T00:00:00.000000Z",
          "releaseNaDayUnknown": false,
          "releaseNaMonthUnknown": false,
          "tcgNotConfirmed": false,
          "setNumber": "SDPD",
          "slug": "pendulum-domination-structure-deck",
          "cardSlugs": null,
          "artworkIds": null,
          "printsCount": null,
          "spoilerTotalPrints": null
        },
        {
          "image": null,
          "format": 1,
          "name": "Structure Deck: Seto Kaiba",
          "releaseEu": "2016-10-20T00:00:00.000000Z",
          "releaseEuDayUnknown": false,
          "releaseEuMonthUnknown": false,
          "releaseNa": "2016-10-21T00:00:00.000000Z",
          "releaseNaDayUnknown": false,
          "releaseNaMonthUnknown": false,
          "tcgNotConfirmed": false,
          "setNumber": "SDKS",
          "slug": "structure-deck-seto-kaiba",
          "cardSlugs": null,
          "artworkIds": null,
          "printsCount": null,
          "spoilerTotalPrints": null
        },
        {
          "image": null,
          "format": 1,
          "name": "Structure Deck: Yugi Muto",
          "releaseEu": "2016-10-20T00:00:00.000000Z",
          "releaseEuDayUnknown": false,
          "releaseEuMonthUnknown": false,
          "releaseNa": "2016-10-21T00:00:00.000000Z",
          "releaseNaDayUnknown": false,
          "releaseNaMonthUnknown": false,
          "tcgNotConfirmed": false,
          "setNumber": "SDMY",
          "slug": "structure-deck-yugi-muto",
          "cardSlugs": null,
          "artworkIds": null,
          "printsCount": null,
          "spoilerTotalPrints": null
        },
        {
          "image": null,
          "format": 1,
          "name": "Master of Pendulum Structure Deck",
          "releaseEu": "2015-12-03T00:00:00.000000Z",
          "releaseEuDayUnknown": false,
          "releaseEuMonthUnknown": false,
          "releaseNa": "2015-12-04T00:00:00.000000Z",
          "releaseNaDayUnknown": false,
          "releaseNaMonthUnknown": false,
          "tcgNotConfirmed": false,
          "setNumber": "SDMP",
          "slug": "master-of-pendulum-structure-deck",
          "cardSlugs": null,
          "artworkIds": null,
          "printsCount": null,
          "spoilerTotalPrints": null
        },
        {
          "image": null,
          "format": 1,
          "name": "Synchron Extreme Structure Deck",
          "releaseEu": "2015-08-27T00:00:00.000000Z",
          "releaseEuDayUnknown": false,
          "releaseEuMonthUnknown": false,
          "releaseNa": "2015-08-28T00:00:00.000000Z",
          "releaseNaDayUnknown": false,
          "releaseNaMonthUnknown": false,
          "tcgNotConfirmed": false,
          "setNumber": "SDSE",
          "slug": "synchron-extreme-structure-deck",
          "cardSlugs": null,
          "artworkIds": null,
          "printsCount": null,
          "spoilerTotalPrints": null
        },
        {
          "image": null,
          "format": 1,
          "name": "HERO Strike Structure Deck",
          "releaseEu": "2015-01-29T00:00:00.000000Z",
          "releaseEuDayUnknown": false,
          "releaseEuMonthUnknown": false,
          "releaseNa": "2015-01-30T00:00:00.000000Z",
          "releaseNaDayUnknown": false,
          "releaseNaMonthUnknown": false,
          "tcgNotConfirmed": false,
          "setNumber": "SDHS",
          "slug": "hero-strike-structure-deck",
          "cardSlugs": null,
          "artworkIds": null,
          "printsCount": null,
          "spoilerTotalPrints": null
        },
        {
          "image": "https://cardcluster.com/storage/sets/SDGR-5219321f2248940b36f9",
          "format": 1,
          "name": "Geargia Rampage Structure Deck",
          "releaseEu": "2014-10-16T00:00:00.000000Z",
          "releaseEuDayUnknown": false,
          "releaseEuMonthUnknown": false,
          "releaseNa": "2014-10-17T00:00:00.000000Z",
          "releaseNaDayUnknown": false,
          "releaseNaMonthUnknown": false,
          "tcgNotConfirmed": false,
          "setNumber": "SDGR",
          "slug": "geargia-rampage-structure-deck",
          "cardSlugs": null,
          "artworkIds": null,
          "printsCount": null,
          "spoilerTotalPrints": null
        },
        {
          "image": null,
          "format": 1,
          "name": "Realm of Light Structure Deck",
          "releaseEu": "2014-06-26T00:00:00.000000Z",
          "releaseEuDayUnknown": false,
          "releaseEuMonthUnknown": false,
          "releaseNa": "2014-06-27T00:00:00.000000Z",
          "releaseNaDayUnknown": false,
          "releaseNaMonthUnknown": false,
          "tcgNotConfirmed": false,
          "setNumber": "SDLI",
          "slug": "realm-of-light-structure-deck",
          "cardSlugs": null,
          "artworkIds": null,
          "printsCount": null,
          "spoilerTotalPrints": null
        },
        {
          "image": null,
          "format": 1,
          "name": "Cyber Dragon Revolution Structure Deck",
          "releaseEu": "2014-02-06T00:00:00.000000Z",
          "releaseEuDayUnknown": false,
          "releaseEuMonthUnknown": false,
          "releaseNa": "2014-02-07T00:00:00.000000Z",
          "releaseNaDayUnknown": false,
          "releaseNaMonthUnknown": false,
          "tcgNotConfirmed": false,
          "setNumber": "SDCR",
          "slug": "cyber-dragon-revolution-structure-deck",
          "cardSlugs": null,
          "artworkIds": null,
          "printsCount": null,
          "spoilerTotalPrints": null
        },
        {
          "image": null,
          "format": 1,
          "name": "Saga of Blue-Eyes White Dragon Structure Deck",
          "releaseEu": "2013-09-12T00:00:00.000000Z",
          "releaseEuDayUnknown": false,
          "releaseEuMonthUnknown": false,
          "releaseNa": "2013-09-13T00:00:00.000000Z",
          "releaseNaDayUnknown": false,
          "releaseNaMonthUnknown": false,
          "tcgNotConfirmed": false,
          "setNumber": "SDBE",
          "slug": "saga-of-blue-eyes-white-dragon-structure-deck",
          "cardSlugs": null,
          "artworkIds": null,
          "printsCount": null,
          "spoilerTotalPrints": null
        },
        {
          "image": null,
          "format": 1,
          "name": "Onslaught of the Fire Kings Structure Deck",
          "releaseEu": "2013-02-07T00:00:00.000000Z",
          "releaseEuDayUnknown": false,
          "releaseEuMonthUnknown": false,
          "releaseNa": "2013-02-08T00:00:00.000000Z",
          "releaseNaDayUnknown": false,
          "releaseNaMonthUnknown": false,
          "tcgNotConfirmed": false,
          "setNumber": "SDOK",
          "slug": "onslaught-of-the-fire-kings-structure-deck",
          "cardSlugs": null,
          "artworkIds": null,
          "printsCount": null,
          "spoilerTotalPrints": null
        },
        {
          "image": null,
          "format": 1,
          "name": "Realm of the Sea Emperor Structure Deck",
          "releaseEu": "2012-10-10T00:00:00.000000Z",
          "releaseEuDayUnknown": false,
          "releaseEuMonthUnknown": false,
          "releaseNa": "2012-10-16T00:00:00.000000Z",
          "releaseNaDayUnknown": false,
          "releaseNaMonthUnknown": false,
          "tcgNotConfirmed": false,
          "setNumber": "SDRE",
          "slug": "realm-of-the-sea-emperor-structure-deck",
          "cardSlugs": null,
          "artworkIds": null,
          "printsCount": null,
          "spoilerTotalPrints": null
        },
        {
          "image": null,
          "format": 1,
          "name": "Samurai Warlords Structure Deck",
          "releaseEu": "2012-06-21T00:00:00.000000Z",
          "releaseEuDayUnknown": false,
          "releaseEuMonthUnknown": false,
          "releaseNa": "2012-06-26T00:00:00.000000Z",
          "releaseNaDayUnknown": false,
          "releaseNaMonthUnknown": false,
          "tcgNotConfirmed": false,
          "setNumber": "SDWA",
          "slug": "samurai-warlords-structure-deck",
          "cardSlugs": null,
          "artworkIds": null,
          "printsCount": null,
          "spoilerTotalPrints": null
        },
        {
          "image": null,
          "format": 1,
          "name": "Dragons Collide Structure Deck",
          "releaseEu": "2012-02-02T00:00:00.000000Z",
          "releaseEuDayUnknown": false,
          "releaseEuMonthUnknown": false,
          "releaseNa": "2012-02-07T00:00:00.000000Z",
          "releaseNaDayUnknown": false,
          "releaseNaMonthUnknown": false,
          "tcgNotConfirmed": false,
          "setNumber": "SDDC",
          "slug": "dragons-collide-structure-deck",
          "cardSlugs": null,
          "artworkIds": null,
          "printsCount": null,
          "spoilerTotalPrints": null
        },
        {
          "image": null,
          "format": 1,
          "name": "Gates of the Underworld Structure Deck",
          "releaseEu": "2011-10-13T00:00:00.000000Z",
          "releaseEuDayUnknown": false,
          "releaseEuMonthUnknown": false,
          "releaseNa": "2011-10-18T00:00:00.000000Z",
          "releaseNaDayUnknown": false,
          "releaseNaMonthUnknown": false,
          "tcgNotConfirmed": false,
          "setNumber": "SDGU",
          "slug": "gates-of-the-underworld-structure-deck",
          "cardSlugs": null,
          "artworkIds": null,
          "printsCount": null,
          "spoilerTotalPrints": null
        },
        {
          "image": null,
          "format": 1,
          "name": "Lost Sanctuary Structure Deck",
          "releaseEu": "2011-06-09T00:00:00.000000Z",
          "releaseEuDayUnknown": false,
          "releaseEuMonthUnknown": false,
          "releaseNa": "2011-06-14T00:00:00.000000Z",
          "releaseNaDayUnknown": false,
          "releaseNaMonthUnknown": false,
          "tcgNotConfirmed": false,
          "setNumber": "SDLS",
          "slug": "lost-sanctuary-structure-deck",
          "cardSlugs": null,
          "artworkIds": null,
          "printsCount": null,
          "spoilerTotalPrints": null
        },
        {
          "image": null,
          "format": 1,
          "name": "Dragunity Legion Structure Deck",
          "releaseEu": "2011-03-03T00:00:00.000000Z",
          "releaseEuDayUnknown": false,
          "releaseEuMonthUnknown": false,
          "releaseNa": "2011-03-08T00:00:00.000000Z",
          "releaseNaDayUnknown": false,
          "releaseNaMonthUnknown": false,
          "tcgNotConfirmed": false,
          "setNumber": "SDDL",
          "slug": "dragunity-legion-structure-deck",
          "cardSlugs": null,
          "artworkIds": null,
          "printsCount": null,
          "spoilerTotalPrints": null
        },
        {
          "image": null,
          "format": 1,
          "name": "Structure Deck: Marik",
          "releaseEu": "2010-10-14T00:00:00.000000Z",
          "releaseEuDayUnknown": false,
          "releaseEuMonthUnknown": false,
          "releaseNa": "2010-10-19T00:00:00.000000Z",
          "releaseNaDayUnknown": false,
          "releaseNaMonthUnknown": false,
          "tcgNotConfirmed": false,
          "setNumber": "SDMA",
          "slug": "structure-deck-marik",
          "cardSlugs": null,
          "artworkIds": null,
          "printsCount": null,
          "spoilerTotalPrints": null
        },
        {
          "image": null,
          "format": 1,
          "name": "Machina Mayhem Structure Deck",
          "releaseEu": "2010-02-18T00:00:00.000000Z",
          "releaseEuDayUnknown": false,
          "releaseEuMonthUnknown": false,
          "releaseNa": "2010-02-23T00:00:00.000000Z",
          "releaseNaDayUnknown": false,
          "releaseNaMonthUnknown": false,
          "tcgNotConfirmed": false,
          "setNumber": "SDMM",
          "slug": "machina-mayhem-structure-deck",
          "cardSlugs": null,
          "artworkIds": null,
          "printsCount": null,
          "spoilerTotalPrints": null
        },
        {
          "image": null,
          "format": 1,
          "name": "Warriors' Strike Structure Deck",
          "releaseEu": "2009-10-22T00:00:00.000000Z",
          "releaseEuDayUnknown": false,
          "releaseEuMonthUnknown": false,
          "releaseNa": "2009-10-27T00:00:00.000000Z",
          "releaseNaDayUnknown": false,
          "releaseNaMonthUnknown": false,
          "tcgNotConfirmed": false,
          "setNumber": "SDWS",
          "slug": "warriors-strike-structure-deck",
          "cardSlugs": null,
          "artworkIds": null,
          "printsCount": null,
          "spoilerTotalPrints": null
        },
        {
          "image": null,
          "format": 1,
          "name": "Spellcaster's Command Structure Deck",
          "releaseEu": "2009-03-31T00:00:00.000000Z",
          "releaseEuDayUnknown": false,
          "releaseEuMonthUnknown": false,
          "releaseNa": "2009-03-31T00:00:00.000000Z",
          "releaseNaDayUnknown": false,
          "releaseNaMonthUnknown": false,
          "tcgNotConfirmed": false,
          "setNumber": "SDSC",
          "slug": "spellcasters-command-structure-deck",
          "cardSlugs": null,
          "artworkIds": null,
          "printsCount": null,
          "spoilerTotalPrints": null
        },
        {
          "image": "https://cardcluster.com/storage/sets/SDZW-eafd28a86e05890826c5",
          "format": 1,
          "name": "Zombie World Structure Deck",
          "releaseEu": "2008-10-21T00:00:00.000000Z",
          "releaseEuDayUnknown": false,
          "releaseEuMonthUnknown": false,
          "releaseNa": "2008-10-21T00:00:00.000000Z",
          "releaseNaDayUnknown": false,
          "releaseNaMonthUnknown": false,
          "tcgNotConfirmed": false,
          "setNumber": "SDZW",
          "slug": "zombie-world-structure-deck",
          "cardSlugs": null,
          "artworkIds": null,
          "printsCount": null,
          "spoilerTotalPrints": null
        },
        {
          "image": null,
          "format": 1,
          "name": "The Dark Emperor Structure Deck",
          "releaseEu": "2008-04-02T00:00:00.000000Z",
          "releaseEuDayUnknown": false,
          "releaseEuMonthUnknown": false,
          "releaseNa": "2008-04-02T00:00:00.000000Z",
          "releaseNaDayUnknown": false,
          "releaseNaMonthUnknown": false,
          "tcgNotConfirmed": false,
          "setNumber": "SDDE",
          "slug": "the-dark-emperor-structure-deck",
          "cardSlugs": null,
          "artworkIds": null,
          "printsCount": null,
          "spoilerTotalPrints": null
        },
        {
          "image": null,
          "format": 1,
          "name": "Rise of the Dragon Lords Structure Deck",
          "releaseEu": "2007-10-24T00:00:00.000000Z",
          "releaseEuDayUnknown": false,
          "releaseEuMonthUnknown": false,
          "releaseNa": "2007-10-24T00:00:00.000000Z",
          "releaseNaDayUnknown": false,
          "releaseNaMonthUnknown": false,
          "tcgNotConfirmed": false,
          "setNumber": "SDRL",
          "slug": "rise-of-the-dragon-lords-structure-deck",
          "cardSlugs": null,
          "artworkIds": null,
          "printsCount": null,
          "spoilerTotalPrints": null
        },
        {
          "image": null,
          "format": 1,
          "name": "Structure Deck: Machine Re-Volt",
          "releaseEu": "2007-01-17T00:00:00.000000Z",
          "releaseEuDayUnknown": false,
          "releaseEuMonthUnknown": false,
          "releaseNa": "2007-01-17T00:00:00.000000Z",
          "releaseNaDayUnknown": false,
          "releaseNaMonthUnknown": false,
          "tcgNotConfirmed": false,
          "setNumber": "SD10",
          "slug": "structure-deck-machine-re-volt",
          "cardSlugs": null,
          "artworkIds": null,
          "printsCount": null,
          "spoilerTotalPrints": null
        },
        {
          "image": null,
          "format": 1,
          "name": "Structure Deck: Dinosaur's Rage",
          "releaseEu": "2006-10-20T00:00:00.000000Z",
          "releaseEuDayUnknown": false,
          "releaseEuMonthUnknown": false,
          "releaseNa": "2006-10-20T00:00:00.000000Z",
          "releaseNaDayUnknown": false,
          "releaseNaMonthUnknown": false,
          "tcgNotConfirmed": false,
          "setNumber": "SD09",
          "slug": "structure-deck-dinosaurs-rage",
          "cardSlugs": null,
          "artworkIds": null,
          "printsCount": null,
          "spoilerTotalPrints": null
        },
        {
          "image": null,
          "format": 1,
          "name": "Structure Deck: Lord of the Storm",
          "releaseEu": "2006-07-12T00:00:00.000000Z",
          "releaseEuDayUnknown": false,
          "releaseEuMonthUnknown": false,
          "releaseNa": "2006-07-12T00:00:00.000000Z",
          "releaseNaDayUnknown": false,
          "releaseNaMonthUnknown": false,
          "tcgNotConfirmed": false,
          "setNumber": "SD8",
          "slug": "structure-deck-lord-of-the-storm",
          "cardSlugs": null,
          "artworkIds": null,
          "printsCount": null,
          "spoilerTotalPrints": null
        },
        {
          "image": null,
          "format": 1,
          "name": "Structure Deck: Invincible Fortress",
          "releaseEu": "2006-05-15T00:00:00.000000Z",
          "releaseEuDayUnknown": false,
          "releaseEuMonthUnknown": false,
          "releaseNa": "2006-05-15T00:00:00.000000Z",
          "releaseNaDayUnknown": false,
          "releaseNaMonthUnknown": false,
          "tcgNotConfirmed": false,
          "setNumber": "SD7",
          "slug": "structure-deck-invincible-fortress",
          "cardSlugs": null,
          "artworkIds": null,
          "printsCount": null,
          "spoilerTotalPrints": null
        },
        {
          "image": null,
          "format": 1,
          "name": "Structure Deck: Spellcaster's Judgment",
          "releaseEu": "2006-01-18T00:00:00.000000Z",
          "releaseEuDayUnknown": false,
          "releaseEuMonthUnknown": false,
          "releaseNa": "2006-01-18T00:00:00.000000Z",
          "releaseNaDayUnknown": false,
          "releaseNaMonthUnknown": false,
          "tcgNotConfirmed": false,
          "setNumber": "SD6",
          "slug": "structure-deck-spellcasters-judgment",
          "cardSlugs": null,
          "artworkIds": null,
          "printsCount": null,
          "spoilerTotalPrints": null
        },
        {
          "image": null,
          "format": 1,
          "name": "Structure Deck: Warrior's Triumph",
          "releaseEu": "2005-10-28T00:00:00.000000Z",
          "releaseEuDayUnknown": false,
          "releaseEuMonthUnknown": false,
          "releaseNa": "2005-10-28T00:00:00.000000Z",
          "releaseNaDayUnknown": false,
          "releaseNaMonthUnknown": false,
          "tcgNotConfirmed": false,
          "setNumber": "SD5",
          "slug": "structure-deck-warriors-triumph",
          "cardSlugs": null,
          "artworkIds": null,
          "printsCount": null,
          "spoilerTotalPrints": null
        },
        {
          "image": null,
          "format": 1,
          "name": "Structure Deck: Fury from the Deep",
          "releaseEu": "2005-05-09T00:00:00.000000Z",
          "releaseEuDayUnknown": false,
          "releaseEuMonthUnknown": false,
          "releaseNa": "2005-05-09T00:00:00.000000Z",
          "releaseNaDayUnknown": false,
          "releaseNaMonthUnknown": false,
          "tcgNotConfirmed": false,
          "setNumber": "SD4",
          "slug": "structure-deck-fury-from-the-deep",
          "cardSlugs": null,
          "artworkIds": null,
          "printsCount": null,
          "spoilerTotalPrints": null
        },
        {
          "image": null,
          "format": 1,
          "name": "Structure Deck: Blaze of Destruction",
          "releaseEu": "2005-05-09T00:00:00.000000Z",
          "releaseEuDayUnknown": false,
          "releaseEuMonthUnknown": false,
          "releaseNa": "2005-05-09T00:00:00.000000Z",
          "releaseNaDayUnknown": false,
          "releaseNaMonthUnknown": false,
          "tcgNotConfirmed": false,
          "setNumber": "SD3",
          "slug": "structure-deck-blaze-of-destruction",
          "cardSlugs": null,
          "artworkIds": null,
          "printsCount": null,
          "spoilerTotalPrints": null
        },
        {
          "image": null,
          "format": 1,
          "name": "Structure Deck: Zombie Madness",
          "releaseEu": "2005-01-01T00:00:00.000000Z",
          "releaseEuDayUnknown": false,
          "releaseEuMonthUnknown": false,
          "releaseNa": "2005-01-01T00:00:00.000000Z",
          "releaseNaDayUnknown": false,
          "releaseNaMonthUnknown": false,
          "tcgNotConfirmed": false,
          "setNumber": "SD2",
          "slug": "structure-deck-zombie-madness",
          "cardSlugs": null,
          "artworkIds": null,
          "printsCount": null,
          "spoilerTotalPrints": null
        },
        {
          "image": null,
          "format": 1,
          "name": "Structure Deck: Dragon's Roar",
          "releaseEu": "2005-01-01T00:00:00.000000Z",
          "releaseEuDayUnknown": false,
          "releaseEuMonthUnknown": false,
          "releaseNa": "2005-01-01T00:00:00.000000Z",
          "releaseNaDayUnknown": false,
          "releaseNaMonthUnknown": false,
          "tcgNotConfirmed": false,
          "setNumber": "SD1",
          "slug": "structure-deck-dragons-roar",
          "cardSlugs": null,
          "artworkIds": null,
          "printsCount": null,
          "spoilerTotalPrints": null
        }
      ],
      "setsCount": 61,
      "format": 1,
      "parent": {
        "name": "Decks",
        "slug": "decks",
        "setsCount": 103,
        "format": 1,
        "parent": null
      }
    },
    "disableSetList": false,
    "format": 1,
    "game": 1,
    "id": 392,
    "image": null,
    "languages": [
      {
        "id": 2259,
        "language": "en",
        "alternateSetNumber": null,
        "alternateLanguageCode": null,
        "firstEdition": true,
        "unlimitedEdition": true,
        "limitedEdition": false
      },
      {
        "id": 2260,
        "language": "it",
        "alternateSetNumber": null,
        "alternateLanguageCode": null,
        "firstEdition": true,
        "unlimitedEdition": true,
        "limitedEdition": false
      },
      {
        "id": 2261,
        "language": "fr",
        "alternateSetNumber": null,
        "alternateLanguageCode": null,
        "firstEdition": true,
        "unlimitedEdition": false,
        "limitedEdition": false
      },
      {
        "id": 2262,
        "language": "de",
        "alternateSetNumber": null,
        "alternateLanguageCode": null,
        "firstEdition": true,
        "unlimitedEdition": false,
        "limitedEdition": false
      }
    ],
    "name": "Structure Deck: Spellcaster's Judgment",
    "next": {
      "name": "Structure Deck: Invincible Fortress",
      "setNumber": "SD7",
      "slug": "structure-deck-invincible-fortress",
      "format": 1,
      "releaseEu": "2006-05-15T00:00:00.000000Z",
      "releaseNa": "2006-05-15T00:00:00.000000Z"
    },
    "previous": {
      "name": "Structure Deck: Warrior's Triumph",
      "setNumber": "SD5",
      "slug": "structure-deck-warriors-triumph",
      "format": 1,
      "releaseEu": "2005-10-28T00:00:00.000000Z",
      "releaseNa": "2005-10-28T00:00:00.000000Z"
    },
    "prints": [
      {
        "cardNumber": "001",
        "card": {
          "name": "Dark Eradicator Warlock",
          "nameEn": "Dark Eradicator Warlock",
          "nameOriginal": null,
          "slug": "dark-eradicator-warlock",
          "archetypeIds": [],
          "cardTypeOrder": "11",
          "cardTypeSection": "monster",
          "firstPrint": "2006-01-18T00:00:00.000000Z",
          "lastPrint": "2016-07-15T00:00:00.000000Z"
        },
        "id": 22933,
        "isFirstPrint": true,
        "prerelease": false,
        "rarity": 5,
        "artworkNumber": null,
        "artworkCategory": null,
        "release": null,
        "image": "https://cardcluster.com/storage/cards/SD6/SD6-DE001-50554c594f",
        "imageIsPlaceholder": true,
        "language": null,
        "copies": null,
        "decoration": null
      },
      {
        "cardNumber": "002",
        "card": {
          "name": "Mythical Beast Cerberus",
          "nameEn": "Mythical Beast Cerberus",
          "nameOriginal": null,
          "slug": "mythical-beast-cerberus",
          "archetypeIds": [
            155
          ],
          "cardTypeOrder": "11",
          "cardTypeSection": "monster",
          "firstPrint": "2006-01-18T00:00:00.000000Z",
          "lastPrint": "2019-04-25T00:00:00.000000Z"
        },
        "id": 22934,
        "isFirstPrint": true,
        "prerelease": false,
        "rarity": 1,
        "artworkNumber": null,
        "artworkCategory": null,
        "release": null,
        "image": "https://cardcluster.com/storage/cards/SD6/SD6-DE002-1686d982df",
        "imageIsPlaceholder": true,
        "language": null,
        "copies": null,
        "decoration": null
      },
      {
        "cardNumber": "003",
        "card": {
          "name": "Dark Magician",
          "nameEn": "Dark Magician",
          "nameOriginal": null,
          "slug": "dark-magician",
          "archetypeIds": [
            45,
            858
          ],
          "cardTypeOrder": "13",
          "cardTypeSection": "monster",
          "firstPrint": "2002-03-08T00:00:00.000000Z",
          "lastPrint": "2026-04-10T00:00:00.000000Z"
        },
        "id": 22935,
        "isFirstPrint": false,
        "prerelease": false,
        "rarity": 1,
        "artworkNumber": 3,
        "artworkCategory": "artwork",
        "release": null,
        "image": "https://cardcluster.com/storage/cards/LC01_25TH/LC01_25TH-DE005-UR-ALT3-11e910eac7",
        "imageIsPlaceholder": true,
        "language": null,
        "copies": null,
        "decoration": null
      },
      {
        "cardNumber": "004",
        "card": {
          "name": "Gemini Elf",
          "nameEn": "Gemini Elf",
          "nameOriginal": null,
          "slug": "gemini-elf",
          "archetypeIds": [
            871
          ],
          "cardTypeOrder": "13",
          "cardTypeSection": "monster",
          "firstPrint": "2003-03-01T00:00:00.000000Z",
          "lastPrint": "2025-11-27T00:00:00.000000Z"
        },
        "id": 22936,
        "isFirstPrint": false,
        "prerelease": false,
        "rarity": 1,
        "artworkNumber": 1,
        "artworkCategory": "artwork",
        "release": null,
        "image": "https://cardcluster.com/storage/cards/YSYR_RP_2018/YSYR_RP_2018-DE006-533bca8d4f",
        "imageIsPlaceholder": true,
        "language": null,
        "copies": null,
        "decoration": null
      },
      {
        "cardNumber": "005",
        "card": {
          "name": "Magician of Faith",
          "nameEn": "Magician of Faith",
          "nameOriginal": null,
          "slug": "magician-of-faith",
          "archetypeIds": [
            858
          ],
          "cardTypeOrder": "11",
          "cardTypeSection": "monster",
          "firstPrint": "2002-06-26T00:00:00.000000Z",
          "lastPrint": "2024-11-08T00:00:00.000000Z"
        },
        "id": 22937,
        "isFirstPrint": false,
        "prerelease": false,
        "rarity": 1,
        "artworkNumber": null,
        "artworkCategory": null,
        "release": null,
        "image": "https://cardcluster.com/storage/cards/SD6/SD6-DE005-ba2343d285",
        "imageIsPlaceholder": true,
        "language": null,
        "copies": 2,
        "decoration": null
      },
      {
        "cardNumber": "006",
        "card": {
          "name": "Skilled Dark Magician",
          "nameEn": "Skilled Dark Magician",
          "nameOriginal": null,
          "slug": "skilled-dark-magician",
          "archetypeIds": [
            45,
            858
          ],
          "cardTypeOrder": "11",
          "cardTypeSection": "monster",
          "firstPrint": "2003-10-10T00:00:00.000000Z",
          "lastPrint": "2024-08-29T00:00:00.000000Z"
        },
        "id": 22938,
        "isFirstPrint": false,
        "prerelease": false,
        "rarity": 1,
        "artworkNumber": null,
        "artworkCategory": null,
        "release": null,
        "image": "https://cardcluster.com/storage/cards/YGLD_RP_2021/YGLD_RP_2021-ENC19-d71309fbcf",
        "imageIsPlaceholder": true,
        "language": null,
        "copies": 2,
        "decoration": null
      },
      {
        "cardNumber": "007",
        "card": {
          "name": "Apprentice Magician",
          "nameEn": "Apprentice Magician",
          "nameOriginal": null,
          "slug": "apprentice-magician",
          "archetypeIds": [],
          "cardTypeOrder": "11",
          "cardTypeSection": "monster",
          "firstPrint": "2003-10-10T00:00:00.000000Z",
          "lastPrint": "2024-11-08T00:00:00.000000Z"
        },
        "id": 22939,
        "isFirstPrint": false,
        "prerelease": false,
        "rarity": 1,
        "artworkNumber": null,
        "artworkCategory": null,
        "release": null,
        "image": "https://cardcluster.com/storage/cards/SGX1/SGX1-ENI05-SCR-5d6e38ce7a",
        "imageIsPlaceholder": true,
        "language": null,
        "copies": 2,
        "decoration": null
      },
      {
        "cardNumber": "008",
        "card": {
          "name": "Chaos Command Magician",
          "nameEn": "Chaos Command Magician",
          "nameOriginal": null,
          "slug": "chaos-command-magician",
          "archetypeIds": [],
          "cardTypeOrder": "11",
          "cardTypeSection": "monster",
          "firstPrint": "2003-10-10T00:00:00.000000Z",
          "lastPrint": "2023-08-25T00:00:00.000000Z"
        },
        "id": 22940,
        "isFirstPrint": false,
        "prerelease": false,
        "rarity": 1,
        "artworkNumber": null,
        "artworkCategory": null,
        "release": null,
        "image": "https://cardcluster.com/storage/cards/SD6/SD6-DE008-6e9c417a1c",
        "imageIsPlaceholder": true,
        "language": null,
        "copies": null,
        "decoration": null
      },
      {
        "cardNumber": "009",
        "card": {
          "name": "Breaker the Magical Warrior",
          "nameEn": "Breaker the Magical Warrior",
          "nameOriginal": null,
          "slug": "breaker-the-magical-warrior",
          "archetypeIds": [
            858
          ],
          "cardTypeOrder": "11",
          "cardTypeSection": "monster",
          "firstPrint": "2003-10-10T00:00:00.000000Z",
          "lastPrint": "2025-08-30T00:00:00.000000Z"
        },
        "id": 22941,
        "isFirstPrint": false,
        "prerelease": false,
        "rarity": 1,
        "artworkNumber": 1,
        "artworkCategory": "artwork",
        "release": null,
        "image": "https://cardcluster.com/storage/cards/SD6/SD6-DE009-9a82ee8248",
        "imageIsPlaceholder": true,
        "language": null,
        "copies": null,
        "decoration": null
      },
      {
        "cardNumber": "010",
        "card": {
          "name": "Royal Magical Library",
          "nameEn": "Royal Magical Library",
          "nameOriginal": null,
          "slug": "royal-magical-library",
          "archetypeIds": [
            827
          ],
          "cardTypeOrder": "11",
          "cardTypeSection": "monster",
          "firstPrint": "2003-10-10T00:00:00.000000Z",
          "lastPrint": "2021-06-10T00:00:00.000000Z"
        },
        "id": 22942,
        "isFirstPrint": false,
        "prerelease": false,
        "rarity": 1,
        "artworkNumber": null,
        "artworkCategory": null,
        "release": null,
        "image": "https://cardcluster.com/storage/cards/OP16/OP16-DE016-999f666b26",
        "imageIsPlaceholder": true,
        "language": null,
        "copies": null,
        "decoration": null
      },
      {
        "cardNumber": "011",
        "card": {
          "name": "Tsukuyomi",
          "nameEn": "Tsukuyomi",
          "nameOriginal": null,
          "slug": "tsukuyomi",
          "archetypeIds": [
            541
          ],
          "cardTypeOrder": "11",
          "cardTypeSection": "monster",
          "firstPrint": "2003-12-01T00:00:00.000000Z",
          "lastPrint": "2023-04-21T00:00:00.000000Z"
        },
        "id": 22943,
        "isFirstPrint": false,
        "prerelease": false,
        "rarity": 1,
        "artworkNumber": null,
        "artworkCategory": null,
        "release": null,
        "image": "https://cardcluster.com/storage/cards/SD6/SD6-DE011-9996802487",
        "imageIsPlaceholder": true,
        "language": null,
        "copies": null,
        "decoration": null
      },
      {
        "cardNumber": "012",
        "card": {
          "name": "Chaos Sorcerer",
          "nameEn": "Chaos Sorcerer",
          "nameOriginal": null,
          "slug": "chaos-sorcerer",
          "archetypeIds": [
            695
          ],
          "cardTypeOrder": "11",
          "cardTypeSection": "monster",
          "firstPrint": "2004-03-01T00:00:00.000000Z",
          "lastPrint": "2025-09-05T00:00:00.000000Z"
        },
        "id": 22944,
        "isFirstPrint": false,
        "prerelease": false,
        "rarity": 1,
        "artworkNumber": null,
        "artworkCategory": null,
        "release": null,
        "image": "https://cardcluster.com/storage/cards/IOC/IOC-DE023-dab1fd2dcc",
        "imageIsPlaceholder": true,
        "language": null,
        "copies": null,
        "decoration": null
      },
      {
        "cardNumber": "013",
        "card": {
          "name": "White Magician Pikeru",
          "nameEn": "White Magician Pikeru",
          "nameOriginal": null,
          "slug": "white-magician-pikeru",
          "archetypeIds": [],
          "cardTypeOrder": "11",
          "cardTypeSection": "monster",
          "firstPrint": "2004-06-15T00:00:00.000000Z",
          "lastPrint": "2022-10-07T00:00:00.000000Z"
        },
        "id": 22945,
        "isFirstPrint": false,
        "prerelease": false,
        "rarity": 1,
        "artworkNumber": null,
        "artworkCategory": null,
        "release": null,
        "image": "https://cardcluster.com/storage/cards/SD6/SD6-DE013-2d027afc5d",
        "imageIsPlaceholder": true,
        "language": null,
        "copies": null,
        "decoration": null
      },
      {
        "cardNumber": "014",
        "card": {
          "name": "Blast Magician",
          "nameEn": "Blast Magician",
          "nameOriginal": null,
          "slug": "blast-magician",
          "archetypeIds": [],
          "cardTypeOrder": "11",
          "cardTypeSection": "monster",
          "firstPrint": "2005-03-01T00:00:00.000000Z",
          "lastPrint": "2024-03-14T00:00:00.000000Z"
        },
        "id": 22946,
        "isFirstPrint": false,
        "prerelease": false,
        "rarity": 1,
        "artworkNumber": null,
        "artworkCategory": null,
        "release": null,
        "image": "https://cardcluster.com/storage/cards/SD6/SD6-DE014-c4c1ead6da",
        "imageIsPlaceholder": true,
        "language": null,
        "copies": null,
        "decoration": null
      },
      {
        "cardNumber": "015",
        "card": {
          "name": "Ebon Magician Curran",
          "nameEn": "Ebon Magician Curran",
          "nameOriginal": null,
          "slug": "ebon-magician-curran",
          "archetypeIds": [],
          "cardTypeOrder": "11",
          "cardTypeSection": "monster",
          "firstPrint": "2005-08-15T00:00:00.000000Z",
          "lastPrint": null
        },
        "id": 22947,
        "isFirstPrint": false,
        "prerelease": false,
        "rarity": 1,
        "artworkNumber": null,
        "artworkCategory": null,
        "release": null,
        "image": "https://cardcluster.com/storage/cards/SD6/SD6-DE015-3174863fd1",
        "imageIsPlaceholder": true,
        "language": null,
        "copies": null,
        "decoration": null
      },
      {
        "cardNumber": "016",
        "card": {
          "name": "Rapid-Fire Magician",
          "nameEn": "Rapid-Fire Magician",
          "nameOriginal": null,
          "slug": "rapid-fire-magician",
          "archetypeIds": [],
          "cardTypeOrder": "11",
          "cardTypeSection": "monster",
          "firstPrint": "2005-11-16T00:00:00.000000Z",
          "lastPrint": null
        },
        "id": 22948,
        "isFirstPrint": false,
        "prerelease": false,
        "rarity": 1,
        "artworkNumber": null,
        "artworkCategory": null,
        "release": null,
        "image": "https://cardcluster.com/storage/cards/SD6/SD6-DE016-f3d25cf81c",
        "imageIsPlaceholder": true,
        "language": null,
        "copies": null,
        "decoration": null
      },
      {
        "cardNumber": "017",
        "card": {
          "name": "Magical Blast",
          "nameEn": "Magical Blast",
          "nameOriginal": null,
          "slug": "magical-blast",
          "archetypeIds": [],
          "cardTypeOrder": "31",
          "cardTypeSection": "spell",
          "firstPrint": "2006-01-18T00:00:00.000000Z",
          "lastPrint": "2019-04-25T00:00:00.000000Z"
        },
        "id": 22949,
        "isFirstPrint": true,
        "prerelease": false,
        "rarity": 1,
        "artworkNumber": null,
        "artworkCategory": null,
        "release": null,
        "image": "https://cardcluster.com/storage/cards/SD6/SD6-DE017-85b0e6d872",
        "imageIsPlaceholder": true,
        "language": null,
        "copies": null,
        "decoration": null
      },
      {
        "cardNumber": "018",
        "card": {
          "name": "Mystical Space Typhoon",
          "nameEn": "Mystical Space Typhoon",
          "nameOriginal": null,
          "slug": "mystical-space-typhoon",
          "archetypeIds": [
            801,
            827,
            781,
            770,
            778,
            813,
            812,
            871,
            858,
            876,
            883,
            911
          ],
          "cardTypeOrder": "34",
          "cardTypeSection": "spell",
          "firstPrint": "2002-09-16T00:00:00.000000Z",
          "lastPrint": "2026-04-10T00:00:00.000000Z"
        },
        "id": 22950,
        "isFirstPrint": false,
        "prerelease": false,
        "rarity": 1,
        "artworkNumber": 1,
        "artworkCategory": "artwork",
        "release": null,
        "image": "https://cardcluster.com/storage/cards/L5DD/L5DD-ENC17-59d7c06019",
        "imageIsPlaceholder": true,
        "language": null,
        "copies": null,
        "decoration": null
      },
      {
        "cardNumber": "019",
        "card": {
          "name": "Nobleman of Crossout",
          "nameEn": "Nobleman of Crossout",
          "nameOriginal": null,
          "slug": "nobleman-of-crossout",
          "archetypeIds": [
            784
          ],
          "cardTypeOrder": "31",
          "cardTypeSection": "spell",
          "firstPrint": "2002-10-20T00:00:00.000000Z",
          "lastPrint": "2025-11-27T00:00:00.000000Z"
        },
        "id": 22951,
        "isFirstPrint": false,
        "prerelease": false,
        "rarity": 1,
        "artworkNumber": null,
        "artworkCategory": null,
        "release": null,
        "image": "https://cardcluster.com/storage/cards/SBC1/SBC1-DEF15-9164246fc2",
        "imageIsPlaceholder": true,
        "language": null,
        "copies": null,
        "decoration": null
      },
      {
        "cardNumber": "020",
        "card": {
          "name": "Premature Burial",
          "nameEn": "Premature Burial",
          "nameOriginal": null,
          "slug": "premature-burial",
          "archetypeIds": [
            841,
            827,
            701,
            702,
            802,
            838,
            858,
            883,
            926
          ],
          "cardTypeOrder": "35",
          "cardTypeSection": "spell",
          "firstPrint": "2002-10-20T00:00:00.000000Z",
          "lastPrint": "2025-11-27T00:00:00.000000Z"
        },
        "id": 22952,
        "isFirstPrint": false,
        "prerelease": false,
        "rarity": 1,
        "artworkNumber": null,
        "artworkCategory": null,
        "release": null,
        "image": "https://cardcluster.com/storage/cards/SD6/SD6-DE020-5ea2572de4",
        "imageIsPlaceholder": true,
        "language": null,
        "copies": null,
        "decoration": null
      },
      {
        "cardNumber": "021",
        "card": {
          "name": "Swords of Revealing Light",
          "nameEn": "Swords of Revealing Light",
          "nameOriginal": null,
          "slug": "swords-of-revealing-light",
          "archetypeIds": [
            697,
            770,
            785,
            866,
            858,
            883,
            919
          ],
          "cardTypeOrder": "31",
          "cardTypeSection": "spell",
          "firstPrint": "2002-03-08T00:00:00.000000Z",
          "lastPrint": "2026-04-10T00:00:00.000000Z"
        },
        "id": 22953,
        "isFirstPrint": false,
        "prerelease": false,
        "rarity": 1,
        "artworkNumber": 1,
        "artworkCategory": "artwork",
        "release": null,
        "image": "https://cardcluster.com/storage/cards/STAS/STAS-EN009-8f2da684f7",
        "imageIsPlaceholder": true,
        "language": null,
        "copies": null,
        "decoration": null
      },
      {
        "cardNumber": "022",
        "card": {
          "name": "Mage Power",
          "nameEn": "Mage Power",
          "nameOriginal": null,
          "slug": "mage-power",
          "archetypeIds": [
            858
          ],
          "cardTypeOrder": "35",
          "cardTypeSection": "spell",
          "firstPrint": "2003-03-01T00:00:00.000000Z",
          "lastPrint": "2025-11-27T00:00:00.000000Z"
        },
        "id": 22954,
        "isFirstPrint": false,
        "prerelease": false,
        "rarity": 1,
        "artworkNumber": null,
        "artworkCategory": null,
        "release": null,
        "image": "https://cardcluster.com/storage/cards/STAS/STAS-EN028-dd1f179aba",
        "imageIsPlaceholder": true,
        "language": null,
        "copies": null,
        "decoration": null
      },
      {
        "cardNumber": "023",
        "card": {
          "name": "Heavy Storm",
          "nameEn": "Heavy Storm",
          "nameOriginal": null,
          "slug": "heavy-storm",
          "archetypeIds": [
            858,
            876
          ],
          "cardTypeOrder": "31",
          "cardTypeSection": "spell",
          "firstPrint": "2002-06-26T00:00:00.000000Z",
          "lastPrint": "2024-11-08T00:00:00.000000Z"
        },
        "id": 22955,
        "isFirstPrint": false,
        "prerelease": false,
        "rarity": 1,
        "artworkNumber": null,
        "artworkCategory": null,
        "release": null,
        "image": "https://cardcluster.com/storage/cards/SD6/SD6-DE023-886e150505",
        "imageIsPlaceholder": true,
        "language": null,
        "copies": null,
        "decoration": null
      },
      {
        "cardNumber": "024",
        "card": {
          "name": "Diffusion Wave-Motion",
          "nameEn": "Diffusion Wave-Motion",
          "nameOriginal": null,
          "slug": "diffusion-wave-motion",
          "archetypeIds": [
            858
          ],
          "cardTypeOrder": "31",
          "cardTypeSection": "spell",
          "firstPrint": "2003-10-10T00:00:00.000000Z",
          "lastPrint": "2021-06-17T00:00:00.000000Z"
        },
        "id": 22956,
        "isFirstPrint": false,
        "prerelease": false,
        "rarity": 1,
        "artworkNumber": null,
        "artworkCategory": null,
        "release": null,
        "image": "https://cardcluster.com/storage/cards/YGLD_RP_2021/YGLD_RP_2021-ENB22-2b29e81a3b",
        "imageIsPlaceholder": true,
        "language": null,
        "copies": null,
        "decoration": null
      },
      {
        "cardNumber": "025",
        "card": {
          "name": "Reload",
          "nameEn": "Reload",
          "nameOriginal": null,
          "slug": "reload",
          "archetypeIds": [
            827,
            781,
            774,
            815,
            919
          ],
          "cardTypeOrder": "34",
          "cardTypeSection": "spell",
          "firstPrint": "2004-03-01T00:00:00.000000Z",
          "lastPrint": "2023-04-21T00:00:00.000000Z"
        },
        "id": 22957,
        "isFirstPrint": false,
        "prerelease": false,
        "rarity": 1,
        "artworkNumber": null,
        "artworkCategory": null,
        "release": null,
        "image": "https://cardcluster.com/storage/cards/SD6/SD6-DE025-14669ccb36",
        "imageIsPlaceholder": true,
        "language": null,
        "copies": null,
        "decoration": null
      },
      {
        "cardNumber": "026",
        "card": {
          "name": "Dark Magic Attack",
          "nameEn": "Dark Magic Attack",
          "nameOriginal": null,
          "slug": "dark-magic-attack",
          "archetypeIds": [
            858
          ],
          "cardTypeOrder": "31",
          "cardTypeSection": "spell",
          "firstPrint": "2004-06-15T00:00:00.000000Z",
          "lastPrint": "2024-08-29T00:00:00.000000Z"
        },
        "id": 22958,
        "isFirstPrint": false,
        "prerelease": false,
        "rarity": 1,
        "artworkNumber": null,
        "artworkCategory": null,
        "release": null,
        "image": "https://cardcluster.com/storage/cards/SD6/SD6-DE026-17d7a5bbde",
        "imageIsPlaceholder": true,
        "language": null,
        "copies": null,
        "decoration": null
      },
      {
        "cardNumber": "027",
        "card": {
          "name": "Spell Absorption",
          "nameEn": "Spell Absorption",
          "nameOriginal": null,
          "slug": "spell-absorption",
          "archetypeIds": [
            876
          ],
          "cardTypeOrder": "33",
          "cardTypeSection": "spell",
          "firstPrint": "2005-03-01T00:00:00.000000Z",
          "lastPrint": "2024-03-01T00:00:00.000000Z"
        },
        "id": 22959,
        "isFirstPrint": false,
        "prerelease": false,
        "rarity": 1,
        "artworkNumber": null,
        "artworkCategory": null,
        "release": null,
        "image": "https://cardcluster.com/storage/cards/INCH/INCH-DE053-321608c601",
        "imageIsPlaceholder": true,
        "language": null,
        "copies": null,
        "decoration": null
      },
      {
        "cardNumber": "028",
        "card": {
          "name": "Lightning Vortex",
          "nameEn": "Lightning Vortex",
          "nameOriginal": null,
          "slug": "lightning-vortex",
          "archetypeIds": [
            702,
            838
          ],
          "cardTypeOrder": "31",
          "cardTypeSection": "spell",
          "firstPrint": "2005-03-01T00:00:00.000000Z",
          "lastPrint": "2024-11-08T00:00:00.000000Z"
        },
        "id": 22960,
        "isFirstPrint": false,
        "prerelease": false,
        "rarity": 1,
        "artworkNumber": null,
        "artworkCategory": null,
        "release": null,
        "image": "https://cardcluster.com/storage/cards/SD6/SD6-DE028-726dc6efd9",
        "imageIsPlaceholder": true,
        "language": null,
        "copies": null,
        "decoration": null
      },
      {
        "cardNumber": "029",
        "card": {
          "name": "Magical Dimension",
          "nameEn": "Magical Dimension",
          "nameOriginal": null,
          "slug": "magical-dimension",
          "archetypeIds": [
            858
          ],
          "cardTypeOrder": "34",
          "cardTypeSection": "spell",
          "firstPrint": "2006-01-18T00:00:00.000000Z",
          "lastPrint": "2024-03-14T00:00:00.000000Z"
        },
        "id": 22961,
        "isFirstPrint": true,
        "prerelease": false,
        "rarity": 1,
        "artworkNumber": null,
        "artworkCategory": null,
        "release": null,
        "image": "https://cardcluster.com/storage/cards/YGLD_RP_2021/YGLD_RP_2021-ENB21-c6c9b3e36d",
        "imageIsPlaceholder": true,
        "language": null,
        "copies": 2,
        "decoration": null
      },
      {
        "cardNumber": "030",
        "card": {
          "name": "Mystic Box",
          "nameEn": "Mystic Box",
          "nameOriginal": null,
          "slug": "mystic-box",
          "archetypeIds": [
            858
          ],
          "cardTypeOrder": "31",
          "cardTypeSection": "spell",
          "firstPrint": "2006-01-18T00:00:00.000000Z",
          "lastPrint": "2021-06-17T00:00:00.000000Z"
        },
        "id": 22962,
        "isFirstPrint": true,
        "prerelease": false,
        "rarity": 1,
        "artworkNumber": null,
        "artworkCategory": null,
        "release": null,
        "image": "https://cardcluster.com/storage/cards/YGLD_RP_2021/YGLD_RP_2021-ENA25-2614dce91f",
        "imageIsPlaceholder": true,
        "language": null,
        "copies": null,
        "decoration": null
      },
      {
        "cardNumber": "031",
        "card": {
          "name": "Nightmare's Steelcage",
          "nameEn": "Nightmare's Steelcage",
          "nameOriginal": null,
          "slug": "nightmares-steelcage",
          "archetypeIds": [
            702,
            799,
            926
          ],
          "cardTypeOrder": "31",
          "cardTypeSection": "spell",
          "firstPrint": "2006-01-18T00:00:00.000000Z",
          "lastPrint": "2016-01-14T00:00:00.000000Z"
        },
        "id": 22963,
        "isFirstPrint": true,
        "prerelease": false,
        "rarity": 1,
        "artworkNumber": null,
        "artworkCategory": null,
        "release": null,
        "image": "https://cardcluster.com/storage/cards/BP02/BP02-DE148-C-cda80c2275",
        "imageIsPlaceholder": true,
        "language": null,
        "copies": null,
        "decoration": null
      },
      {
        "cardNumber": "032",
        "card": {
          "name": "Call of the Haunted",
          "nameEn": "Call of the Haunted",
          "nameOriginal": null,
          "slug": "call-of-the-haunted",
          "archetypeIds": [
            827,
            782,
            799,
            773,
            871,
            883,
            911,
            926,
            919
          ],
          "cardTypeOrder": "42",
          "cardTypeSection": "trap",
          "firstPrint": "2002-10-20T00:00:00.000000Z",
          "lastPrint": "2025-11-27T00:00:00.000000Z"
        },
        "id": 22964,
        "isFirstPrint": false,
        "prerelease": false,
        "rarity": 1,
        "artworkNumber": 1,
        "artworkCategory": "artwork",
        "release": null,
        "image": "https://cardcluster.com/storage/cards/STAX/STAX-EN014-3b84667cd9",
        "imageIsPlaceholder": true,
        "language": null,
        "copies": null,
        "decoration": null
      },
      {
        "cardNumber": "033",
        "card": {
          "name": "Spell Shield Type-8",
          "nameEn": "Spell Shield Type-8",
          "nameOriginal": null,
          "slug": "spell-shield-type-8",
          "archetypeIds": [],
          "cardTypeOrder": "43",
          "cardTypeSection": "trap",
          "firstPrint": "2003-10-10T00:00:00.000000Z",
          "lastPrint": "2012-05-29T00:00:00.000000Z"
        },
        "id": 22965,
        "isFirstPrint": false,
        "prerelease": false,
        "rarity": 1,
        "artworkNumber": null,
        "artworkCategory": null,
        "release": null,
        "image": "https://cardcluster.com/storage/cards/SD6/SD6-DE033-0dbf5fadc0",
        "imageIsPlaceholder": true,
        "language": null,
        "copies": null,
        "decoration": null
      },
      {
        "cardNumber": "034",
        "card": {
          "name": "Pitch-Black Power Stone",
          "nameEn": "Pitch-Black Power Stone",
          "nameOriginal": null,
          "slug": "pitch-black-power-stone",
          "archetypeIds": [],
          "cardTypeOrder": "42",
          "cardTypeSection": "trap",
          "firstPrint": "2003-10-10T00:00:00.000000Z",
          "lastPrint": "2023-08-25T00:00:00.000000Z"
        },
        "id": 22966,
        "isFirstPrint": false,
        "prerelease": false,
        "rarity": 1,
        "artworkNumber": null,
        "artworkCategory": null,
        "release": null,
        "image": "https://cardcluster.com/storage/cards/SD6/SD6-DE034-68a2c59af1",
        "imageIsPlaceholder": true,
        "language": null,
        "copies": null,
        "decoration": null
      },
      {
        "cardNumber": "035",
        "card": {
          "name": "Divine Wrath",
          "nameEn": "Divine Wrath",
          "nameOriginal": null,
          "slug": "divine-wrath",
          "archetypeIds": [
            802,
            821
          ],
          "cardTypeOrder": "43",
          "cardTypeSection": "trap",
          "firstPrint": "2004-12-01T00:00:00.000000Z",
          "lastPrint": null
        },
        "id": 22967,
        "isFirstPrint": false,
        "prerelease": false,
        "rarity": 1,
        "artworkNumber": null,
        "artworkCategory": null,
        "release": null,
        "image": "https://cardcluster.com/storage/cards/SD6/SD6-DE035-ca2d86a7f4",
        "imageIsPlaceholder": true,
        "language": null,
        "copies": null,
        "decoration": null
      },
      {
        "cardNumber": "036",
        "card": {
          "name": "Magic Cylinder",
          "nameEn": "Magic Cylinder",
          "nameOriginal": null,
          "slug": "magic-cylinder",
          "archetypeIds": [
            781,
            858,
            872,
            911,
            919
          ],
          "cardTypeOrder": "41",
          "cardTypeSection": "trap",
          "firstPrint": "2003-03-01T00:00:00.000000Z",
          "lastPrint": "2026-04-10T00:00:00.000000Z"
        },
        "id": 22968,
        "isFirstPrint": false,
        "prerelease": false,
        "rarity": 1,
        "artworkNumber": 1,
        "artworkCategory": "artwork",
        "release": null,
        "image": "https://cardcluster.com/storage/cards/STAS/STAS-EN027-3d67f409f0",
        "imageIsPlaceholder": true,
        "language": null,
        "copies": null,
        "decoration": null
      }
    ],
    "printsCount": null,
    "releaseEu": "2006-01-18T00:00:00.000000Z",
    "releaseEuDayUnknown": false,
    "releaseEuMonthUnknown": false,
    "releaseNa": "2006-01-18T00:00:00.000000Z",
    "releaseNaDayUnknown": false,
    "releaseNaMonthUnknown": false,
    "tournamentLegal": null,
    "setNumber": "SD6",
    "slug": "structure-deck-spellcasters-judgment",
    "scanCounts": {
      "en": 0,
      "de": 19
    }
  }
}